openadapt_grounding/__init__.py
openadapt_grounding/builder.py
openadapt_grounding/collector.py
openadapt_grounding/demo.py
openadapt_grounding/locator.py
openadapt_grounding/types.py
openadapt_grounding/deploy/.dockerignore
openadapt_grounding/deploy/Dockerfile
openadapt_grounding/deploy/__init__.py
openadapt_grounding/deploy/__main__.py
openadapt_grounding/deploy/config.py
openadapt_grounding/deploy/deploy.py
openadapt_grounding/deploy/uitars/Dockerfile
openadapt_grounding/deploy/uitars/__init__.py
openadapt_grounding/deploy/uitars/__main__.py
openadapt_grounding/deploy/uitars/deploy.py
openadapt_grounding/eval/__init__.py
openadapt_grounding/eval/__main__.py
openadapt_grounding/eval/cli.py
openadapt_grounding/eval/config.py
openadapt_grounding/eval/dataset/__init__.py
openadapt_grounding/eval/dataset/schema.py
openadapt_grounding/eval/dataset/synthetic.py
openadapt_grounding/eval/methods/__init__.py
openadapt_grounding/eval/methods/base.py
openadapt_grounding/eval/methods/cropping.py
openadapt_grounding/eval/methods/omniparser.py
openadapt_grounding/eval/methods/uitars.py
openadapt_grounding/eval/metrics/__init__.py
openadapt_grounding/eval/metrics/compute.py
openadapt_grounding/eval/metrics/types.py
openadapt_grounding/eval/results/__init__.py
openadapt_grounding/eval/results/compare.py
openadapt_grounding/eval/results/storage.py
openadapt_grounding/eval/visualization/__init__.py
openadapt_grounding/eval/visualization/charts.py
openadapt_grounding/eval/visualization/tables.py
openadapt_grounding/parsers/__init__.py
openadapt_grounding/parsers/base.py
openadapt_grounding/parsers/omniparser.py
openadapt_grounding/parsers/uitars.py
openadapt_grounding/providers/__init__.py
openadapt_grounding/providers/anthropic.py
openadapt_grounding/providers/base.py
openadapt_grounding/providers/google.py
openadapt_grounding/providers/openai.py
openadapt_grounding-0.1.2.dist-info/METADATA
openadapt_grounding-0.1.2.dist-info/WHEEL
openadapt_grounding-0.1.2.dist-info/licenses/LICENSE
openadapt_grounding-0.1.2.dist-info/RECORD
