Metadata-Version: 2.4
Name: openadapt-grounding
Version: 0.1.2
Summary: Robust UI element localization for automation
Project-URL: Homepage, https://github.com/OpenAdaptAI/openadapt-grounding
Project-URL: Repository, https://github.com/OpenAdaptAI/openadapt-grounding
Project-URL: Documentation, https://github.com/OpenAdaptAI/openadapt-grounding#readme
Project-URL: Issues, https://github.com/OpenAdaptAI/openadapt-grounding/issues
Project-URL: Changelog, https://github.com/OpenAdaptAI/openadapt-grounding/releases
Author-email: Richard Abrich <richard@openadapt.ai>
Maintainer-email: OpenAdaptAI <info@openadapt.ai>
License-Expression: MIT
License-File: LICENSE
Keywords: automation,grounding,localization,ocr,omniparser,ui,vision,vlm
Classifier: Development Status :: 3 - Alpha
Classifier: Intended Audience :: Developers
Classifier: License :: OSI Approved :: MIT License
Classifier: Programming Language :: Python :: 3
Classifier: Programming Language :: Python :: 3.10
Classifier: Programming Language :: Python :: 3.11
Classifier: Programming Language :: Python :: 3.12
Classifier: Topic :: Scientific/Engineering :: Artificial Intelligence
Classifier: Topic :: Software Development :: Libraries :: Python Modules
Requires-Python: >=3.10
Requires-Dist: pillow>=10.0.0
Requires-Dist: pytesseract>=0.3.10
Requires-Dist: requests>=2.31.0
Provides-Extra: all
Requires-Dist: anthropic>=0.40.0; extra == 'all'
Requires-Dist: boto3>=1.34.0; extra == 'all'
Requires-Dist: fire>=0.5.0; extra == 'all'
Requires-Dist: google-genai>=1.0.0; extra == 'all'
Requires-Dist: matplotlib>=3.7.0; extra == 'all'
Requires-Dist: openai>=1.0.0; extra == 'all'
Requires-Dist: paramiko>=3.4.0; extra == 'all'
Requires-Dist: pydantic-settings>=2.0.0; extra == 'all'
Requires-Dist: pytest>=8.0.0; extra == 'all'
Requires-Dist: ruff>=0.1.0; extra == 'all'
Requires-Dist: tqdm>=4.65.0; extra == 'all'
Provides-Extra: deploy
Requires-Dist: boto3>=1.34.0; extra == 'deploy'
Requires-Dist: fire>=0.5.0; extra == 'deploy'
Requires-Dist: paramiko>=3.4.0; extra == 'deploy'
Requires-Dist: pydantic-settings>=2.0.0; extra == 'deploy'
Provides-Extra: dev
Requires-Dist: pytest>=8.0.0; extra == 'dev'
Requires-Dist: ruff>=0.1.0; extra == 'dev'
Provides-Extra: eval
Requires-Dist: fire>=0.5.0; extra == 'eval'
Requires-Dist: matplotlib>=3.7.0; extra == 'eval'
Requires-Dist: pydantic-settings>=2.0.0; extra == 'eval'
Requires-Dist: tqdm>=4.65.0; extra == 'eval'
Provides-Extra: providers
Requires-Dist: anthropic>=0.40.0; extra == 'providers'
Requires-Dist: google-genai>=1.0.0; extra == 'providers'
Requires-Dist: openai>=1.0.0; extra == 'providers'
Provides-Extra: providers-anthropic
Requires-Dist: anthropic>=0.40.0; extra == 'providers-anthropic'
Provides-Extra: providers-google
Requires-Dist: google-genai>=1.0.0; extra == 'providers-google'
Provides-Extra: providers-openai
Requires-Dist: openai>=1.0.0; extra == 'providers-openai'
Provides-Extra: uitars
Requires-Dist: openai>=1.0.0; extra == 'uitars'
